opencv_webcam/__init__.py
opencv_webcam/opencv_webcam.py
opencv_webcam/requirements.txt
opencv_webcam/utils/__init__.py
opencv_webcam/utils/args_yaml.py
opencv_webcam/utils/check_opt.py
opencv_webcam/utils/compress.py
opencv_webcam/utils/fonts_opt.py
opencv_webcam/utils/frame_opt.py
opencv_webcam/utils/log.py
opencv_webcam/utils/path_opt.py
opencv_webcam/utils/plot.py
opencv_webcam/utils/rm_bgColor.py
opencv_webcam/utils/sys_opt.py
opencv_webcam/utils/time_format.py
opencv_webcam_script-0.9.1.dist-info/LICENSE
opencv_webcam_script-0.9.1.dist-info/METADATA
opencv_webcam_script-0.9.1.dist-info/WHEEL
opencv_webcam_script-0.9.1.dist-info/top_level.txt
opencv_webcam_script-0.9.1.dist-info/RECORD
