Metadata-Version: 2.1
Name: opencv-webcam-script
Version: 0.9.1
Summary: webcam opencv script
Home-page: https://gitee.com/CV_Lab/opencv_webcam
Author: Yifu Zeng
Author-email: zyfiy1314@163.com
License: GPL-3.0 Licence
Keywords: opencv,webcam
Platform: any
License-File: LICENSE
